scan_3d_by_xxp/__init__.py
scan_3d_by_xxp/scan3d.py
scan_3d_by_xxp-1.2.dist-info/METADATA
scan_3d_by_xxp-1.2.dist-info/WHEEL
scan_3d_by_xxp-1.2.dist-info/top_level.txt
scan_3d_by_xxp-1.2.dist-info/RECORD
