Metadata-Version: 2.1
Name: scan-3d-by-xxp
Version: 1.2
Summary: scan 3d package by xxp
Home-page: UNKNOWN
Author: Xinping Xu
Author-email: <xuxinping92@gmail.com>
License: UNKNOWN
Keywords: python,first package
Platform: UNKNOWN
Classifier: Development Status :: 3 - Alpha
Classifier: Intended Audience :: Developers
Classifier: Programming Language :: Python :: 2
Classifier: Programming Language :: Python :: 3
Classifier: Operating System :: MacOS :: MacOS X
Classifier: Operating System :: Microsoft :: Windows
Classifier: Operating System :: POSIX :: Linux
Requires-Dist: numpy
Requires-Dist: pandas
